locate_pixelcolor_numbacuda/LICENSE
locate_pixelcolor_numbacuda/README.MD
locate_pixelcolor_numbacuda/__init__.py
locate_pixelcolor_numbacuda/requirements.txt
locate_pixelcolor_numbacuda/thirdparty.json
locate_pixelcolor_numbacuda-0.12.dist-info/LICENSE.rst
locate_pixelcolor_numbacuda-0.12.dist-info/METADATA
locate_pixelcolor_numbacuda-0.12.dist-info/WHEEL
locate_pixelcolor_numbacuda-0.12.dist-info/top_level.txt
locate_pixelcolor_numbacuda-0.12.dist-info/RECORD
