Metadata-Version: 2.1
Name: locate-pixelcolor-numbacuda
Version: 0.12
Summary: RGB search with numba.cuda - 10 x faster than numpy
Home-page: https://github.com/hansalemaos/locate_pixelcolor_numbacuda
Author: Johannes Fischer
Author-email: aulasparticularesdealemaosp@gmail.com
License: MIT
Keywords: numpy,numba,CUDA,rgb,search
Classifier: Development Status :: 4 - Beta
Classifier: Programming Language :: Python :: 3 :: Only
Classifier: Programming Language :: Python :: 3.10
Classifier: Topic :: Software Development :: Libraries :: Python Modules
Classifier: Topic :: Utilities
License-File: LICENSE.rst
Requires-Dist: numba
Requires-Dist: numpy
